obsplotlib/__init__.py
obsplotlib/_version.py
obsplotlib/attribdict.py
obsplotlib/cli.py
obsplotlib/data.py
obsplotlib/frechet.py
obsplotlib/plot.py
obsplotlib/process.py
obsplotlib/section.py
obsplotlib/seismogram.py
obsplotlib/signal.py
obsplotlib/stream_utils.py
obsplotlib/traveltime.py
obsplotlib/utils.py
obsplotlib/window.py
obsplotlib/dataclasses/__init__.py
obsplotlib/dataclasses/cmt.py
obsplotlib/dataclasses/scardec_stf.py
obsplotlib-0.5.2.dist-info/LICENSE
obsplotlib-0.5.2.dist-info/METADATA
obsplotlib-0.5.2.dist-info/WHEEL
obsplotlib-0.5.2.dist-info/entry_points.txt
obsplotlib-0.5.2.dist-info/top_level.txt
obsplotlib-0.5.2.dist-info/RECORD
