Metadata-Version: 2.1
Name: obsplotlib
Version: 0.5.2
Summary: Plotting Tools for waveforms from Obspy
Author-email: Lucas Sawade <lsawade@princeton.edu>
Maintainer-email: Lucas Sawade <lsawade@princeton.edu>
License: GNU GENERAL PUBLIC LICENSE
Project-URL: Homepage, https://github.com/lsawade/obsplotlib
Project-URL: Bug Reports, https://github.com/lsawade/obsplotlib/issues
Project-URL: Source, https://github.com/lsawade/obsplotlib
Project-URL: Documentation, http://lsawade.github.io/obsplotlib
Keywords: Obspy,Seismology,Plotting
Classifier: Programming Language :: Python :: 3.10
Classifier: Programming Language :: Python :: 3.11
Classifier: License :: OSI Approved :: GNU General Public License v3 or later (GPLv3+)
Classifier: Operating System :: OS Independent
Requires-Python: >=3.10
License-File: LICENSE
Requires-Dist: obspy
Requires-Dist: matplotlib
Requires-Dist: numpy
Requires-Dist: scipy
Provides-Extra: docs
Requires-Dist: sphinx <6.0 ; extra == 'docs'
Requires-Dist: furo ; extra == 'docs'
Requires-Dist: sphinx-design ; extra == 'docs'
Requires-Dist: sphinx-togglebutton ; extra == 'docs'
Requires-Dist: sphinx-gallery ; extra == 'docs'
Requires-Dist: numpydoc ; extra == 'docs'
